mim_ocr/__init__.py
mim_ocr/backends/__init__.py
mim_ocr/backends/aws_textract.py
mim_ocr/backends/backend.py
mim_ocr/backends/google_vision.py
mim_ocr/backends/tesseract.py
mim_ocr/data_model/__init__.py
mim_ocr/data_model/box.py
mim_ocr/data_model/box_functions.py
mim_ocr/exceptions/__init__.py
mim_ocr/exceptions/smooth_job_context.py
mim_ocr/heuristics/__init__.py
mim_ocr/heuristics/basic_features.py
mim_ocr/heuristics/extract_simple_results.py
mim_ocr/heuristics/feature.py
mim_ocr/heuristics/fuzzy_matching_keyword_feature.py
mim_ocr/heuristics/heuristic_analysis.py
mim_ocr/heuristics/keyword_feature.py
mim_ocr/heuristics/pol_roberta_ner_on_device.py
mim_ocr/heuristics/regex_feature.py
mim_ocr/image/__init__.py
mim_ocr/image/image.py
mim_ocr/image/transformations.py
mim_ocr/optional_elements/__init__.py
mim_ocr/optional_elements/easy_ocr/__init__.py
mim_ocr/optional_elements/ner_feature/NER_feature.py
mim_ocr/optional_elements/ner_feature/__init__.py
mim_ocr/pipeline/__init__.py
mim_ocr/pipeline/batch_processing.py
mim_ocr/pipeline/pipeline.py
mim_ocr/preprocessing/__init__.py
mim_ocr/preprocessing/deskew.py
mim_ocr/preprocessing/reorient.py
mim_ocr/utils/__init__.py
mim_ocr/utils/class_utils.py
mim_ocr/utils/notebook_utils.py
mim_ocr/utils/validators.py
mim_ocr/visualization/__init__.py
mim_ocr/visualization/visualize_result.py
mim_ocr-0.0.10.dist-info/LICENSE.txt
mim_ocr-0.0.10.dist-info/METADATA
mim_ocr-0.0.10.dist-info/WHEEL
mim_ocr-0.0.10.dist-info/top_level.txt
mim_ocr-0.0.10.dist-info/RECORD
