Metadata-Version: 2.1
Name: mim-ocr
Version: 0.0.10
Summary: Tool for using different OCR engines and process their results using common data structures.
Author-email: Barbara Mroczek <barbara.mroczek@mim.ai>
Project-URL: Homepage, https://github.com/mim-solutions/MIM-OCR
Project-URL: Bug Tracker, https://github.com/mim-solutions/MIM-OCR/issues
Classifier: Programming Language :: Python :: 3
Classifier: License :: OSI Approved :: MIT License
Classifier: Operating System :: POSIX :: Linux
Requires-Python: <3.11,>=3.9
License-File: LICENSE.txt
Requires-Dist: matplotlib (~=3.5.1)
Requires-Dist: numpy (~=1.22.2)
Requires-Dist: opencv-python (==4.5.4.60)
Requires-Dist: opencv-python-headless (==4.5.4.60)
Requires-Dist: pandas (~=1.4.0)
Requires-Dist: pdf2image
Requires-Dist: Pillow (==9.0.1)
Requires-Dist: boto3
Requires-Dist: deskew (~=0.10.40)
Requires-Dist: google-cloud-storage
Requires-Dist: google-cloud-vision (>=3.0.0)
Requires-Dist: hyperscan (==0.3.3)
Requires-Dist: jsonpickle
Requires-Dist: loguru
Requires-Dist: omegaconf
Requires-Dist: openpyxl
Requires-Dist: pptree
Requires-Dist: pytesseract (~=0.3.8)
Requires-Dist: strsimpy
Requires-Dist: symspellpy
Requires-Dist: tqdm
